LICENSE
MANIFEST.in
README.md
setup.cfg
setup.py
keystoneclient_rackspace/__init__.py
keystoneclient_rackspace/v2_0.py
python_keystoneclient_rackspace.egg-info/PKG-INFO
python_keystoneclient_rackspace.egg-info/SOURCES.txt
python_keystoneclient_rackspace.egg-info/dependency_links.txt
python_keystoneclient_rackspace.egg-info/entry_points.txt
python_keystoneclient_rackspace.egg-info/pbr.json
python_keystoneclient_rackspace.egg-info/requires.txt
python_keystoneclient_rackspace.egg-info/top_level.txt