Metadata-Version: 1.1
Name: python-keystoneclient-rackspace
Version: 0.1.3
Summary: Rackspace Auth Plugin for OpenStack Clients.
Home-page: https://github.com/testeddoughnut/python-keystoneclient-rackspace
Author: M. David Bennett
Author-email: mdavidbennett@syntheticworks.com
License: Apache License, Version 2.0
Download-URL: https://github.com/testeddoughnut/python-keystoneclient-rackspace/tarball/v0.1.3
Platform: UNKNOWN
Classifier: Development Status :: 5 - Production/Stable
Classifier: Environment :: Console
Classifier: Intended Audience :: Developers
Classifier: Intended Audience :: Information Technology
Classifier: License :: OSI Approved :: Apache Software License
Classifier: Operating System :: OS Independent
Classifier: Environment :: OpenStack
Classifier: Programming Language :: Python
